README.rst
setup.py
medgen/__init__.py
medgen/api.py
medgen/config.py
medgen/exceptions.py
medgen/log.py
medgen/vocab.py
medgen/annotate/__init__.py
medgen/annotate/concept.py
medgen/annotate/disease.py
medgen/annotate/gene.py
medgen/annotate/ncbi_variant_old.py
medgen/annotate/personalgenomes.py
medgen/annotate/pubmed.py
medgen/annotate/variant.py
medgen/config/medgen.default.ini
medgen/db/__init__.py
medgen/db/boolean.py
medgen/db/clinvar.py
medgen/db/dataset.py
medgen/db/gene.py
medgen/db/hugo.py
medgen/db/medgen.py
medgen/db/personalgenomes.py
medgen/db/pubmed.py
medgen/parse/__init__.py
medgen/parse/common.py
medgen/parse/concept.py
medgen/parse/gene.py
medgen_prime.egg-info/PKG-INFO
medgen_prime.egg-info/SOURCES.txt
medgen_prime.egg-info/dependency_links.txt
medgen_prime.egg-info/requires.txt
medgen_prime.egg-info/top_level.txt